JianYingDraft/__init__.py
JianYingDraft/core/__init__.py
JianYingDraft/core/draft.py
JianYingDraft/core/media.py
JianYingDraft/core/mediaAudio.py
JianYingDraft/core/mediaEffect.py
JianYingDraft/core/mediaFactory.py
JianYingDraft/core/mediaImage.py
JianYingDraft/core/mediaText.py
JianYingDraft/core/mediaVideo.py
JianYingDraft/core/template.py
JianYingDraft/template/draft_content.json
JianYingDraft/template/draft_meta_info.json
JianYingDraft/utils/__init__.py
JianYingDraft/utils/dataStruct.py
JianYingDraft/utils/innerBizTypes.py
JianYingDraft/utils/tools.py
LICENSE
README.md
jianyingdraft_py-1.0.4.dist-info/LICENSE
jianyingdraft_py-1.0.4.dist-info/METADATA
jianyingdraft_py-1.0.4.dist-info/WHEEL
jianyingdraft_py-1.0.4.dist-info/RECORD
