Metadata-Version: 2.1
Name: JianYingDraft.PY
Version: 1.0.4
Summary: 帮助剪映快速生成草稿的方案
License: MIT
Author: 解大劦
Author-email: develope@163.com
Requires-Python: >=3.12,<4.0
Classifier: License :: OSI Approved :: MIT License
Classifier: Programming Language :: Python :: 3
Classifier: Programming Language :: Python :: 3.12
Requires-Dist: basiclibrary-py (>=0.6.10,<0.7.0)
Requires-Dist: pymediainfo (>=6.1.0,<7.0.0)
Requires-Dist: pytest (>=8.1.1,<9.0.0)
